LICENSE
MANIFEST.in
README.md
setup.py
map4/__init__.py
map4/__version__.py
map4/cli.py
map4/map4.py
map4.egg-info/PKG-INFO
map4.egg-info/SOURCES.txt
map4.egg-info/dependency_links.txt
map4.egg-info/entry_points.txt
map4.egg-info/requires.txt
map4.egg-info/top_level.txt
tests/test_cli.py
tests/test_map4.py
tests/test_version_code.py
tests/test_visualize.py