Metadata-Version: 2.1
Name: map4
Version: 1.1.3
Summary: MinHashed AtomPair Fingerprint of Radius 2
Home-page: https://github.com/reymond-group/map4
Author: Alice Capecchi
License: MIT
Classifier: Development Status :: 4 - Beta
Classifier: License :: OSI Approved :: MIT License
Classifier: Programming Language :: Python :: 3
License-File: LICENSE
Requires-Dist: mhfp
Requires-Dist: numpy
Requires-Dist: rdkit
Requires-Dist: tqdm
Requires-Dist: scikit-learn
Requires-Dist: matplotlib
Provides-Extra: test
Requires-Dist: pytest; extra == "test"
Requires-Dist: pytest-cov; extra == "test"
Requires-Dist: pytest-readme; extra == "test"
Requires-Dist: pandas; extra == "test"
Requires-Dist: validate_version_code; extra == "test"
